pupquiz/__init__.py
pupquiz/__main__.py
pupquiz/canvas.py
pupquiz/config.py
pupquiz/graphics.py
pupquiz/pupquiz.py
pupquiz/session.py
pupquiz/word_iterator.py
pupquiz/resources/__init__.py
pupquiz/resources/default-assets.zip
pupquiz/resources/folder-off.png
pupquiz/resources/folder-on.png
pupquiz/resources/icon.ico
pupquiz-0.0.20.dist-info/LICENSE
pupquiz-0.0.20.dist-info/METADATA
pupquiz-0.0.20.dist-info/WHEEL
pupquiz-0.0.20.dist-info/top_level.txt
pupquiz-0.0.20.dist-info/RECORD
