Metadata-Version: 2.1
Name: pupquiz
Version: 0.0.20
Summary: Facilitates vocabulary acquisition
Home-page: https://github.com/kovadarra/pupquiz
Author: kovadarra
Author-email: kovadarra@users.noreply.github.com
License: UNKNOWN
Platform: UNKNOWN
Classifier: Programming Language :: Python :: 3
Classifier: License :: OSI Approved :: MIT License
Classifier: Operating System :: OS Independent
Requires-Python: >=3.8
Requires-Dist: pillow (>=7.1.2)
Requires-Dist: pysimplegui (>=4.20.0)
Requires-Dist: gTTS (>=2.1.1)
Requires-Dist: playsound (>=1.2.2)
Requires-Dist: matplotlib (>=3.1.3)
